melnykmathlibrary/__init__.py
melnykmathlibrary/myfunctions.py
melnykmathlibrary-0.1.0.dist-info/METADATA
melnykmathlibrary-0.1.0.dist-info/WHEEL
melnykmathlibrary-0.1.0.dist-info/top_level.txt
melnykmathlibrary-0.1.0.dist-info/RECORD
