Metadata-Version: 2.1
Name: melnykmathlibrary
Version: 0.1.0
Summary: My first Python library
Home-page: UNKNOWN
Author: Melnyk Iryna
License: UNKNOWN
Platform: UNKNOWN
